Metadata-Version: 2.1
Name: argvns
Version: 0.2
Summary: a wrapper around argparse that allows for static typing
Home-page: https://github.com/lilellia/argvns
Download-URL: https://github.com/lilellia/argvns/archive/refs/tags/v0.1.tar.gz
Author: Lily Ellington
Author-email: lilell_@outlook.com
License: MIT
Keywords: argv,argparse
Classifier: Development Status :: 3 - Alpha
Classifier: Intended Audience :: Developers
Classifier: Topic :: Software Development :: Build Tools
Classifier: License :: OSI Approved :: MIT License
Classifier: Programming Language :: Python :: 3
Classifier: Programming Language :: Python :: 3.8
Classifier: Programming Language :: Python :: 3.9
Classifier: Programming Language :: Python :: 3.10
Classifier: Programming Language :: Python :: 3.11
Classifier: Programming Language :: Python :: 3.12
Classifier: Programming Language :: Python :: 3.13
License-File: LICENSE
